{
  "awesome": "https://awesome-github-stats.azurewebsites.net/user-stats/guylepage3/rank",
  "rankPoints": {
    "commits": 1,
    "contributedToNotOwnerRepositories": 100,
    "contributedToOwnRepositories": 1,
    "createdRepositories": 1,
    "directStars": 5,
    "followers": 1,
    "indirectStars": 0.3,
    "issues": 5,
    "pullRequests": 1,
    "pullRequestsToAnotherRepositories": 10,
    "commitsToMyRepositories": 1,
    "commitsToAnotherRepositories": 1,
    "contributedTo": 1
  },
  "userStats": {
    "commitsToMyRepositories": 241,
    "lastFetch": "2023-04-02T23:18:43.855297+00:00",
    "login": "guylepage3",
    "name": "Guy Lepage",
    "pullRequests": 374,
    "commits": 12182,
    "commitsToAnotherRepositories": 11941,
    "pullRequestsToAnotherRepositories": 372,
    "issues": 1569,
    "createdRepositories": 11,
    "directStars": 31,
    "indirectStars": 614090,
    "contributedTo": 76,
    "contributedToOwnRepositories": 6,
    "contributedToNotOwnerRepositories": 70,
    "followers": 144
  },
  "level": "S+",
  "score": 227922
}